asttrs/__init__.py
asttrs/_ast.py
asttrs/_base.py
asttrs/_py3_10.py
asttrs/_py3_11.py
asttrs/_py3_12.py
asttrs/_py3_7.py
asttrs/_py3_8.py
asttrs/_py3_9.py
asttrs/utils.py
asttrs-1.3.0.dist-info/LICENSE
asttrs-1.3.0.dist-info/METADATA
asttrs-1.3.0.dist-info/WHEEL
asttrs-1.3.0.dist-info/top_level.txt
asttrs-1.3.0.dist-info/RECORD
