Metadata-Version: 2.1
Name: asttrs
Version: 1.3.0
Summary: A attrs-style wrapper for python ast
Author-email: ryanchao2012 <ryanchao2012@gmail.com>
License: MIT
Project-URL: repository, https://github.com/ryanchao2012/asttrs
Classifier: Programming Language :: Python :: 3.7
Classifier: Programming Language :: Python :: 3.8
Classifier: Programming Language :: Python :: 3.9
Classifier: Programming Language :: Python :: 3.10
Classifier: Programming Language :: Python :: 3.11
Classifier: Programming Language :: Python :: 3.12
Requires-Python: >=3.7
License-File: LICENSE
Requires-Dist: attrs
Requires-Dist: black
Requires-Dist: cattrs
Requires-Dist: isort
Requires-Dist: ast-decompiler
